{"cameraMode":{"drawMode":0,"name":"Shaded","section":"Shading Mode"},"sceneLighting":true,"audioPlay":false,"sceneViewState":{"showFog":true,"showMaterialUpdate":false,"showSkybox":true,"showFlares":true,"showImageEffects":true,"showParticleSystems":true},"in2DMode":false,"pivot":{"x":-10.126569747924805,"y":-43.7899169921875,"z":14.497712135314942},"rotation":{"x":-0.37958189845085146,"y":0.5985816121101379,"z":-0.38393351435661318,"w":-0.5917959809303284},"size":38.751773834228519,"orthographic":false}